[{"preview":"94","uid":"34235","mobile":"on","desktop":"on","padding_top":"0","padding_bottom":"0","padding_right":"0","padding_left":"0","padding_type":"px","m_padding_top":"0","m_padding_bottom":"0","m_padding_right":"0","m_padding_left":"0","m_padding_type":"px","border_color":"rgba(0,0,0)","border_outer":"on","skin_outer":"on","m_fs":"on","fs":"on","width":"950","title_check":"off","subtitle_check":"off","posts_per_page":"4","filter":"post_tag","byline_off":"off","excerpt_off":"on","excerpt_length":"20","fs_limit":"off","post_tag":[{"value":27,"label":"Featured"}],"label":"Featured Grid","t_padding_top":"0","t_padding_bottom":"0","t_padding_right":"0","t_padding_left":"0","t_padding_type":"px","skin":"0","skin_color":"rgb(255,255,255)","divider_top_onoff":"off","divider_bottom_onoff":"off","margin_type":"px","t_margin_type":"px","m_margin_type":"px","meta_background_padding":"30","meta_background_img_opacity":"100","meta_background_color":"rgb(255,255,255)","skin_img_opacity":"100","skin_parallax":"off","animation_onoff":"off","animation_stagger":"off","boxed_content":"off","fi_off":"off","border_check":0,"margin_bottom":"0","margin_top":"0","t_margin_bottom":"0","t_margin_top":"0","m_margin_bottom":"0","m_margin_top":"0","z_index":0,"border_top":"0","border_bottom":"0","border_right":"0","border_left":"0","border_color_2":"rgba(0,0,0)","gradient_direction":"30","meta_background":0,"article_shadow":"","meta_background_text_color":0,"meta_background_img":"","columns_m":"1","skin_text_color":0,"skin_img":"","divider_skin_bottom":"","divider_skin_top":"","divider_color_top":"#fff","divider_color_botom":"#fff","mobile_design":0,"animation_type":0,"divider_top":0,"divider_bottom":0,"title":"","subtitle":"","pretitle_check":"","pretitle":"","flip":"","flipstack":"","order":0,"offset":0,"meta_location":0,"load_more":0},{"preview":"50","uid":"39853","mobile":"off","desktop":"on","padding_top":"30","padding_bottom":"30","padding_right":"0","padding_left":"0","padding_type":"px","m_padding_top":"30","m_padding_bottom":"30","m_padding_right":"0","m_padding_left":"0","m_padding_type":"px","border_color":"#1E1E1E","border_outer":"on","skin_outer":"on","fs":"on","width":"950","ad_type":"1","small_print_check":"off","ad_img":"https://demos.codetipi.com/zeen-foto/wp-content/uploads/sites/13/2018/08/da-xl-tech.png","ad_img_2x":"https://demos.codetipi.com/zeen-foto/wp-content/uploads/sites/13/2018/08/da-xl-tech@2x.png","ad_img_id":"1036","ad_img_2x_id":"1037","border_check":"2","border_bottom":"1","label":"970x90 Ad","t_padding_top":"30","t_padding_bottom":"30","t_padding_right":"0","t_padding_left":"0","t_padding_type":"px","skin":"0","skin_color":"rgb(255,255,255)","divider_top_onoff":"off","divider_bottom_onoff":"off","margin_type":"px","t_margin_type":"px","m_margin_type":"px","meta_background_padding":"30","meta_background_img_opacity":"100","meta_background_color":"rgb(255,255,255)","skin_img_opacity":"100","skin_parallax":"off","animation_onoff":"off","animation_stagger":"off","boxed_content":"off","margin_bottom":"0","margin_top":"0","t_margin_bottom":"0","t_margin_top":"0","m_margin_bottom":"0","m_margin_top":"0","z_index":0,"border_top":"0","border_right":"0","border_left":"0","border_color_2":"rgba(0,0,0)","gradient_direction":"30","meta_background":0,"article_shadow":"","meta_background_text_color":0,"meta_background_img":"","columns_m":"1","skin_text_color":0,"skin_img":"","divider_skin_bottom":"","divider_skin_top":"","divider_color_top":"#fff","divider_color_botom":"#fff","mobile_design":0,"animation_type":0,"divider_top":0,"divider_bottom":0,"m_fs":"","title_check":"","subtitle_check":"","title":"","subtitle":"","pretitle_check":"","pretitle":"","ad_url":"","new_tab":"","custom_content":"","small_print":""},{"preview":"62","uid":"80613","mobile":"on","desktop":"on","padding_top":"60","padding_bottom":"30","padding_right":"0","padding_left":"0","padding_type":"px","m_padding_top":"30","m_padding_bottom":"30","m_padding_right":"0","m_padding_left":"0","m_padding_type":"px","border_color":"rgba(0,0,0)","border_outer":"on","skin_outer":"on","fs":"off","width":"950","title_check":"off","subtitle_check":"off","posts_per_page":"3","filter":"posts","byline_off":"on","excerpt_off":"on","excerpt_length":"20","fs_limit":"off","posts":[{"value":17,"label":"Billion Year Old Stars"},{"value":51,"label":"Space Exploration 2030"},{"value":49,"label":"The Sun Corona"}],"label":"Featured 3","t_padding_top":"30","t_padding_bottom":"0","t_padding_right":"0","t_padding_left":"0","t_padding_type":"px","skin":"0","skin_color":"rgb(255,255,255)","divider_top_onoff":"off","divider_bottom_onoff":"off","m_fs":"off","parallax":"off","margin_type":"px","t_margin_type":"px","m_margin_type":"px","meta_background_padding":"30","meta_background_img_opacity":"100","meta_background_color":"rgb(255,255,255)","skin_img_opacity":"100","skin_parallax":"off","animation_onoff":"off","animation_stagger":"off","boxed_content":"off","fi_off":"off","border_check":0,"margin_bottom":"0","margin_top":"0","t_margin_bottom":"0","t_margin_top":"0","m_margin_bottom":"0","m_margin_top":"0","z_index":0,"border_top":"0","border_bottom":"0","border_right":"0","border_left":"0","border_color_2":"rgba(0,0,0)","gradient_direction":"30","meta_background":0,"article_shadow":"","meta_background_text_color":0,"meta_background_img":"","columns_m":"1","skin_text_color":0,"skin_img":"","divider_skin_bottom":"","divider_skin_top":"","divider_color_top":"#fff","divider_color_botom":"#fff","mobile_design":0,"animation_type":0,"divider_top":0,"divider_bottom":0,"title":"","subtitle":"","pretitle_check":"","pretitle":"","flip":"","flipstack":"","order":0,"offset":0,"meta_location":0,"load_more":0},{"preview":"39","uid":"87860","mobile":"on","desktop":"on","padding_top":"1","padding_bottom":"30","padding_right":"0","padding_left":"0","padding_type":"px","m_padding_top":"30","m_padding_bottom":"30","m_padding_right":"0","m_padding_left":"0","m_padding_type":"px","border_color":"rgba(0,0,0)","border_outer":"on","skin":"2","skin_outer":"off","width":"950","coor_2":"30","label":"Dark Line","fs":"on","t_padding_top":"1","t_padding_bottom":"30","t_padding_right":"0","t_padding_left":"0","t_padding_type":"px","skin_color":"rgb(255,255,255)","divider_top_onoff":"off","divider_bottom_onoff":"off","margin_type":"px","t_margin_type":"px","m_margin_type":"px","meta_background_padding":"30","meta_background_img_opacity":"100","meta_background_color":"rgb(255,255,255)","skin_img_opacity":"100","skin_parallax":"off","animation_onoff":"off","animation_stagger":"off","boxed_content":"off","border_check":0,"margin_bottom":"0","margin_top":"0","t_margin_bottom":"0","t_margin_top":"0","m_margin_bottom":"0","m_margin_top":"0","z_index":0,"border_top":"0","border_bottom":"0","border_right":"0","border_left":"0","border_color_2":"rgba(0,0,0)","gradient_direction":"30","meta_background":0,"article_shadow":"","meta_background_text_color":0,"meta_background_img":"","columns_m":"1","skin_text_color":0,"skin_img":"","divider_skin_bottom":"","divider_skin_top":"","divider_color_top":"#fff","divider_color_botom":"#fff","mobile_design":0,"animation_type":0,"divider_top":0,"divider_bottom":0,"m_fs":"","title_check":"","subtitle_check":"","title":"","subtitle":"","pretitle_check":"","pretitle":""},{"preview":"39","uid":"47310","mobile":"on","desktop":"on","padding_top":"30","padding_bottom":"30","padding_right":"0","padding_left":"0","padding_type":"px","m_padding_top":"30","m_padding_bottom":"30","m_padding_right":"0","m_padding_left":"0","m_padding_type":"px","border_color":"rgba(0,0,0)","border_outer":"on","skin_outer":"off","width":"950","coor_2":"30","label":"Spacing","fs":"off","t_padding_top":"1","t_padding_bottom":"30","t_padding_right":"0","t_padding_left":"0","t_padding_type":"px","skin":"0","skin_color":"rgb(255,255,255)","divider_top_onoff":"off","divider_bottom_onoff":"off","m_fs":"off","margin_type":"px","t_margin_type":"px","m_margin_type":"px","meta_background_padding":"30","meta_background_img_opacity":"100","meta_background_color":"rgb(255,255,255)","skin_img_opacity":"100","skin_parallax":"off","animation_onoff":"off","animation_stagger":"off","boxed_content":"off","border_check":0,"margin_bottom":"0","margin_top":"0","t_margin_bottom":"0","t_margin_top":"0","m_margin_bottom":"0","m_margin_top":"0","z_index":0,"border_top":"0","border_bottom":"0","border_right":"0","border_left":"0","border_color_2":"rgba(0,0,0)","gradient_direction":"30","meta_background":0,"article_shadow":"","meta_background_text_color":0,"meta_background_img":"","columns_m":"1","skin_text_color":0,"skin_img":"","divider_skin_bottom":"","divider_skin_top":"","divider_color_top":"#fff","divider_color_botom":"#fff","mobile_design":0,"animation_type":0,"divider_top":0,"divider_bottom":0,"title_check":"","subtitle_check":"","title":"","subtitle":"","pretitle_check":"","pretitle":""},{"preview":"300","uid":"82555","mobile":"on","desktop":"on","padding_top":"30","padding_bottom":"30","padding_right":"0","padding_left":"0","padding_type":"px","m_padding_top":"0","m_padding_bottom":"0","m_padding_right":"0","m_padding_left":"0","m_padding_type":"px","border_color":"rgba(0,0,0)","border_outer":"on","skin_outer":"on","m_fs":"on","width":"950","title_check":"on","subtitle_check":"off","title":"<p>The Archives</p>","layout":"1","label":"Archives","byline_off":"off","excerpt_off":"off","excerpt_length":"12","t_padding_top":"30","t_padding_bottom":"30","t_padding_right":"0","t_padding_left":"0","t_padding_type":"px","skin":"0","skin_color":"rgb(255,255,255)","divider_top_onoff":"off","divider_bottom_onoff":"off","margin_type":"px","t_margin_type":"px","m_margin_type":"px","meta_background_padding":"30","meta_background_img_opacity":"100","meta_background_color":"rgb(255,255,255)","skin_img_opacity":"100","skin_parallax":"off","animation_onoff":"off","animation_stagger":"off","boxed_content":"off","border_check":0,"margin_bottom":"0","margin_top":"0","t_margin_bottom":"0","t_margin_top":"0","m_margin_bottom":"0","m_margin_top":"0","z_index":0,"border_top":"0","border_bottom":"0","border_right":"0","border_left":"0","border_color_2":"rgba(0,0,0)","gradient_direction":"30","meta_background":0,"article_shadow":"","meta_background_text_color":0,"meta_background_img":"","columns_m":"1","skin_text_color":0,"skin_img":"","divider_skin_bottom":"","divider_skin_top":"","divider_color_top":"#fff","divider_color_botom":"#fff","mobile_design":0,"animation_type":0,"divider_top":0,"divider_bottom":0,"fs":"","subtitle":"","pretitle_check":"","pretitle":"","sidebar":"sidebar-default","pagination":0,"cat__not_in":"","offset":0},{"preview":"25","uid":"86332","mobile":"on","desktop":"on","border_check":"2","padding_top":"45","padding_bottom":"45","padding_right":"0","padding_left":"0","padding_type":"px","m_padding_top":"30","m_padding_bottom":"30","m_padding_right":"0","m_padding_left":"0","m_padding_type":"px","border_color":"#1B1B1B","fs":"on","width":"950","title_check":"on","subtitle_check":"on","title":"<p>Must Reads</p>","posts_per_page":"4","filter":"post_tag","order":"2","byline_off":"off","excerpt_off":"on","excerpt_length":"20","border_outer":"on","skin_outer":"on","border_bottom":"1","post_tag":[{"value":18,"label":"Water"}],"border_top":"1","label":"Must Reads","t_padding_top":"30","t_padding_bottom":"30","t_padding_right":"0","t_padding_left":"0","t_padding_type":"px","skin":"0","skin_color":"rgb(255,255,255)","divider_top_onoff":"off","divider_bottom_onoff":"off","margin_type":"px","t_margin_type":"px","m_margin_type":"px","meta_background_padding":"30","meta_background_img_opacity":"100","meta_background_color":"rgb(255,255,255)","skin_img_opacity":"100","skin_parallax":"off","animation_onoff":"off","animation_stagger":"off","boxed_content":"on","fi_off":"off","margin_bottom":"0","margin_top":"0","t_margin_bottom":"0","t_margin_top":"0","m_margin_bottom":"0","m_margin_top":"0","z_index":0,"border_right":"0","border_left":"0","border_color_2":"rgba(0,0,0)","gradient_direction":"30","meta_background":0,"article_shadow":"","meta_background_text_color":0,"meta_background_img":"","columns_m":"1","skin_text_color":0,"skin_img":"","divider_skin_bottom":"","divider_skin_top":"","divider_color_top":"#fff","divider_color_botom":"#fff","mobile_design":0,"animation_type":0,"divider_top":0,"divider_bottom":0,"m_fs":"off","subtitle":"","pretitle_check":"","pretitle":"","posts_per_row":4,"flip":"","flipstack":"","offset":0,"meta_location":0,"load_more":0},{"preview":"49","uid":"40315","mobile":"on","desktop":"on","padding_top":"30","padding_bottom":"30","padding_right":"0","padding_left":"0","padding_type":"px","m_padding_top":"30","m_padding_bottom":"30","m_padding_right":"0","m_padding_left":"0","m_padding_type":"px","border_color":"rgb(181, 181, 181)","border_outer":"on","skin_outer":"on","fs":"on","width":"950","title_check":"on","subtitle_check":"on","pretitle_check":"on","pretitle":"<p class=\"fontfam-1\"><strong style=\"color: #b7b7b7\">CALL TO ACTION BLOCK</strong></p>","custom_content":"<p class=\"fontfam-1\">COSMOS VOLUME 2</p>","cta_content":"<p>This is a call to action block from the tipi builder.&nbsp;</p><p>Increase visitor clicks to something specific.</p>","parallax":"on","img_bg_overlay":"rgb(0,0,0,0)","coor_4":"11.71","coor_6":"48.29","m_coor_6":"100","m_coor_2":"100","img_bg":"https://demos.codetipi.com/zeen-foto/wp-content/uploads/sites/13/2018/08/zeen-foto-cta.jpg","img_bg_id":"1029","button_color":"#3d85c6","button_color_2":"#ffffff","button_check":"on","button_text":"<p><a target=\"_blank\" href=\"https://1.envato.market/yKqeW\"><strong>ORDER NOW</strong></a></p>","button_check_2":"off","button_style_1":"1","button_size":"1","sticky":"off","label":"CTA For Vol 2","position":"4","t_padding_top":"30","t_padding_bottom":"30","t_padding_right":"0","t_padding_left":"0","t_padding_type":"px","skin":"0","skin_color":"rgb(255,255,255)","divider_top_onoff":"off","divider_bottom_onoff":"off","m_fs":"on","button_design":"1","video_bg":"off","margin_type":"px","t_margin_type":"px","m_margin_type":"px","meta_background_padding":"30","meta_background_img_opacity":"100","meta_background_color":"rgb(255,255,255)","skin_img_opacity":"100","skin_parallax":"off","animation_onoff":"off","animation_stagger":"off","boxed_content":"off","border_check":0,"margin_bottom":"0","margin_top":"0","t_margin_bottom":"0","t_margin_top":"0","m_margin_bottom":"0","m_margin_top":"0","z_index":0,"border_top":"0","border_bottom":"0","border_right":"0","border_left":"0","border_color_2":"rgba(0,0,0)","gradient_direction":"30","meta_background":0,"article_shadow":"","meta_background_text_color":0,"meta_background_img":"","columns_m":"1","skin_text_color":0,"skin_img":"","divider_skin_bottom":"","divider_skin_top":"","divider_color_top":"#fff","divider_color_botom":"#fff","mobile_design":0,"animation_type":0,"divider_top":0,"divider_bottom":0,"title":"","subtitle":"","meta_padding_d":"30","meta_padding_t":"30","meta_padding_m":15,"meta_width_d":"50","meta_width_t":"80","meta_width_m":100,"content_font_size_m":14,"content_font_size_t":"16","content_font_size_d":"20","title_font_size_m":24,"title_font_size_t":36,"title_font_size_d":"60","m_position":"5","button_text_2":"","button_style_2":"","height_d":"800","height_t":"350","height_m":"350","height_d_type":"px","height_t_type":"px","height_m_type":"px"}]